datatalk/__init__.py
datatalk/__version__.py
datatalk/analyzer.py
datatalk/core.py
datatalk/exporter.py
datatalk/extractor.py
datatalk/plugin.py
datatalk-0.2.5.dist-info/LICENSE
datatalk-0.2.5.dist-info/METADATA
datatalk-0.2.5.dist-info/WHEEL
datatalk-0.2.5.dist-info/RECORD
