Metadata-Version: 2.1
Name: datatalk
Version: 0.2.5
Summary: Talk to data
Author: longhao
Author-email: hal.long@outlook.com
Requires-Python: >=3.9,<4.0
Classifier: Programming Language :: Python :: 3
Classifier: Programming Language :: Python :: 3.9
Classifier: Programming Language :: Python :: 3.10
Classifier: Programming Language :: Python :: 3.11
Classifier: Programming Language :: Python :: 3.12
Classifier: Programming Language :: Python :: 3.13
Requires-Dist: python-calamine (>=0.3.1,<0.4.0)
Requires-Dist: xlsxwriter (>=3.2.0,<4.0.0)
